<?xml version="1.0" encoding="UTF-8"?>
<!DOCTYPE hibernate-mapping PUBLIC "-//Hibernate/Hibernate Mapping DTD 3.0//EN" "http://www.hibernate.org/dtd/hibernate-mapping-3.0.dtd">
<!-- Generated 14-ene-2018 19:02:21 by Hibernate Tools 4.3.1 -->
<hibernate-mapping>
  <class name="com.siscogescorp.modelo.LcEstatus" optimistic-lock="version" schema="public" table="lc_estatus">
    <id name="idEstatus" type="int">
      <column name="id_estatus"/>
      <generator class="assigned"/>
    </id>
    <property name="descripcion" type="string">
      <column length="100" name="descripcion"/>
    </property>
    <property name="fechaCreacion" type="timestamp">
      <column length="29" name="fecha_creacion"/>
    </property>
    <property name="estado" type="string">
      <column length="1" name="estado"/>
    </property>
    <set fetch="select" inverse="true" lazy="true" name="lcDatosDeudoreses" table="lc_datos_deudores">
      <key>
        <column name="status"/>
      </key>
      <one-to-many class="com.siscogescorp.modelo.LcDatosDeudores"/>
    </set>
  </class>
</hibernate-mapping>
